code/__init__.py
code/datetime_intel.py
code/gadget.py
py_package_template12313213-1.0.0.dist-info/licenses/LICENSE
py_package_template12313213-1.0.0.dist-info/METADATA
py_package_template12313213-1.0.0.dist-info/WHEEL
py_package_template12313213-1.0.0.dist-info/top_level.txt
py_package_template12313213-1.0.0.dist-info/RECORD
