Metadata-Version: 2.4
Name: py_package_template12313213
Version: 1.0.0
Summary: A sample python package to start sharing your code with the world
Home-page: https://github.com/thinh-vu/py_packaging_template123
Author: Thinh Vu
Author-email: mrthinh@live.com
Requires-Python: >=3.7
License-File: LICENSE
Requires-Dist: trafilatura
Dynamic: license-file
